constellationfs/__init__.py
constellationfs/gateway.py
constellationfs/ipfsnode.py
constellationfs/result.py
constellationfs-0.3.7.dist-info/DESCRIPTION.rst
constellationfs-0.3.7.dist-info/METADATA
constellationfs-0.3.7.dist-info/RECORD
constellationfs-0.3.7.dist-info/WHEEL
constellationfs-0.3.7.dist-info/metadata.json
constellationfs-0.3.7.dist-info/top_level.txt
