Metadata-Version: 2.0
Name: constellationfs
Version: 0.3.7
Summary: Incentivation system for IPFS pinning via Stellar micropayments
Home-page: https://github.com/ilrico/constellation-fs
Author: ilrico
Author-email: admin@constellation-fs.org
License: UNKNOWN
Keywords: IPFS,Stellar
Platform: UNKNOWN
Classifier: Programming Language :: Python :: 3
Classifier: License :: OSI Approved :: MIT License
Classifier: Operating System :: OS Independent
